{
  "frontmatter": {
    "title": "ヴァンドーム",
    "menu": "ヴァンドーム",
    "created": "05-01-2017, 23:13",
    "date": "01-03-2018, 10:15",
    "modified": "01-03-2018, 10:42",
    "metadata": {
      "description": "ヴァンドーム広場（Place Vendôme）の１７世紀の様子を把握できる資料。",
      "keywords": "ヴァンドーム",
      "imageTitle": "ヴァンドーム",
      "imageLegend": "１７世紀のヴァンドーム広場の風景。"
    },
    "significantLinks": ["https://github.com/tidiview/francois-vidit.com/blob/develop/user/sites/docs/pages/01.home/01.paris/02.vendome/chapter.ja.md"],
    "specialty": ["ヴァンドーム広場"]
  },
  "articleBody": ""
}